restart/__init__.py
restart/base.py
restart/data.py
restart/demand.py
restart/demand_dict.py
restart/demand_jhu.py
restart/demand_mitre.py
restart/demand_who.py
restart/epi.py
restart/epi_dict.py
restart/epi_table.py
restart/filtermodel.py
restart/financial.py
restart/financial_dict.py
restart/financial_table.py
restart/inventory.py
restart/inventory_dict.py
restart/load.py
restart/load_csv.py
restart/log.py
restart/main.py
restart/mobility.py
restart/mobility_dict.py
restart/mobility_table.py
restart/model.py
restart/module_test.py
restart/organization.py
restart/organization_dict.py
restart/output.py
restart/population.py
restart/population_dict.py
restart/population_oes.py
restart/population_wa.py
restart/resource_dict.py
restart/resourcemodel.py
restart/restart.py
restart/util.py
restart/validate.py
restart_test-2.5.0.7.1.0.1.dist-info/METADATA
restart_test-2.5.0.7.1.0.1.dist-info/WHEEL
restart_test-2.5.0.7.1.0.1.dist-info/top_level.txt
restart_test-2.5.0.7.1.0.1.dist-info/RECORD
